[
  {
    "titre": "Deniola new in african ankara print jacket and trouser set"
  },
  {
    "titre": "Robe infini imprimé africain, maxi convertible infinity dress, robe infinity, robe en pagne"
  },
  {
    "titre": "Top à basque"
  },
  {
    "titre": "Robe meïma"
  },
  {
    "titre": "Robe longue chemise parapluies et papillons"
  },
  {
    "titre": "Tshirt femme oversize - africa power"
  },
  {
    "titre": "Combinaison couché de soleil"
  },
  {
    "titre": "Robe chemise parapluie et papillons en amour"
  },
  {
    "titre": "Coco betty waxy"
  },
  {
    "titre": "Combinaison hyré bogolan"
  },
  {
    "titre": "Robe portefeuille fleur de mariage beige"
  },
  {
    "titre": "Kimono en mousseline de soie ankara tribal / camouflage"
  },
  {
    "titre": "Md jozi asymmetric midi (orange brûlé)"
  },
  {
    "titre": "T-shirt \"lady bogolan\" black & gold"
  },
  {
    "titre": "Coco betty unity"
  },
  {
    "titre": "Robe que jeunesse se fasse"
  },
  {
    "titre": "Robe en wax boutonée"
  },
  {
    "titre": "Robe cache coeur soie bogolan best seller"
  },
  {
    "titre": "Robe de soirée en wax"
  },
  {
    "titre": "Maillot de bain kente"
  },
  {
    "titre": "Crop top en mousseline clémentine"
  },
  {
    "titre": "Ensemble deux pièces lakeli"
  },
  {
    "titre": "Robe"
  },
  {
    "titre": "Robe ample manches courtes en wax ( pagne africain )"
  },
  {
    "titre": "T-shirt \"lady bogolan\""
  },
  {
    "titre": "Short fleur de mariage"
  },
  {
    "titre": "Chemise homme classe addis abeba wax"
  },
  {
    "titre": "Jupe miss angola bordeaux"
  },
  {
    "titre": "Robe foi africaine imprimé"
  },
  {
    "titre": "Robe en wax"
  },
  {
    "titre": "Imane set - black"
  },
  {
    "titre": "T-shirt \"miss bogolan\" black & gold"
  },
  {
    "titre": "Little miss rosa parks gris t-shirt"
  },
  {
    "titre": "Combinaison md kigali palazzo"
  },
  {
    "titre": "Nina robe maxi infini imprimé africain / robe maxi africaine / robe ankara"
  },
  {
    "titre": "Pareo fluide bogolan"
  },
  {
    "titre": "Robe t-shirt lady bogolan black & gold"
  },
  {
    "titre": "Robe camara en tissu tableau jaune"
  },
  {
    "titre": "T-shirt \"mister bogolan chapeau\""
  },
  {
    "titre": "Robe en wax cauris"
  },
  {
    "titre": "Robe droite en batik imprimé africain"
  },
  {
    "titre": "Havana maxi - livraison gratuite ❤️"
  },
  {
    "titre": "Maillot de bain avec motif bogolan"
  },
  {
    "titre": "Robe longue imprimée africaine viviana"
  },
  {
    "titre": "Robe portefeuille nénuphar"
  },
  {
    "titre": "Combinaison delu à imprimé africain"
  },
  {
    "titre": "T-shirt \"bogolan boy\""
  },
  {
    "titre": "Coco betty la tchipeuse"
  },
  {
    "titre": "Jupe plumes"
  },
  {
    "titre": "Robe épaules dénudées fleurs de mariage royale"
  },
  {
    "titre": "T-shirt femme gris chiné - \"afro hair for afro queen*\" ( rasta version)"
  },
  {
    "titre": "Robe maxi imprimé tribal"
  },
  {
    "titre": "Tchalla"
  },
  {
    "titre": "Mini robe jean addis-abeba"
  },
  {
    "titre": "Robe ankara élastique sepa"
  },
  {
    "titre": "Robe chemise md aya"
  },
  {
    "titre": "Top en wax oversized"
  },
  {
    "titre": "Top kimono imprimé africain zandra"
  },
  {
    "titre": "Robe katrina à imprimé africain"
  },
  {
    "titre": "Distanciation"
  },
  {
    "titre": "Robe cece imprimée africaine"
  },
  {
    "titre": "Robe graphique bi-matière"
  },
  {
    "titre": "Robe mi-longue à imprimé africain malaika khanga"
  },
  {
    "titre": "Crop top imprimé africain konadu"
  }
]